fauxdantic/__init__.py
fauxdantic/config.py
fauxdantic/core.py
fauxdantic/exceptions.py
fauxdantic/generators/__init__.py
fauxdantic/generators/collections.py
fauxdantic/generators/numbers.py
fauxdantic/generators/strings.py
fauxdantic/type_handling.py
fauxdantic/types/__init__.py
fauxdantic/types/constraints.py
fauxdantic/types/handlers.py
fauxdantic/utils/__init__.py
fauxdantic/utils/unique.py
fauxdantic/value_generation.py
fauxdantic-0.1.13.dist-info/LICENSE
fauxdantic-0.1.13.dist-info/METADATA
fauxdantic-0.1.13.dist-info/WHEEL
fauxdantic-0.1.13.dist-info/RECORD
