Metadata-Version: 2.3
Name: fauxdantic
Version: 0.1.13
Summary: A library for generating fake Pydantic models for testing and development purposes
License: MIT
Keywords: pydantic,testing,faker,fake-data
Author: John A. Dungan
Author-email: johnadungan@gmail.com
Requires-Python: >=3.11
Classifier: Development Status :: 4 - Beta
Classifier: Intended Audience :: Developers
Classifier: License :: OSI Approved :: MIT License
Classifier: Programming Language :: Python :: 3
Classifier: Programming Language :: Python :: 3.11
Classifier: Programming Language :: Python :: 3.12
Classifier: Programming Language :: Python :: 3.13
Classifier: Programming Language :: Python :: 3.10
Classifier: Programming Language :: Python :: 3.9
Classifier: Topic :: Software Development :: Libraries :: Python Modules
Classifier: Topic :: Software Development :: Testing
Requires-Dist: faker (>=37.1.0,<38.0.0)
Requires-Dist: pydantic (>=2.11.3,<3.0.0)
Project-URL: Documentation, https://github.com/jdungan/fauxdantic#readme
Project-URL: Repository, https://github.com/jdungan/fauxdantic
